sgl2020/__init__.py
sgl2020/data_wrapping.py
sgl2020/descriptions/__init__.py
sgl2020/descriptions/_flight.py
sgl2020/descriptions/_flt1002.py
sgl2020/descriptions/_flt1003.py
sgl2020/descriptions/_flt1004.py
sgl2020/descriptions/_flt1005.py
sgl2020/descriptions/_flt1006.py
sgl2020/descriptions/_flt1007.py
sgl2020/descriptions/_sensor.py
sgl2020/descriptions/raw/Flt1002_readme.txt
sgl2020/descriptions/raw/Flt1003_readme.txt
sgl2020/descriptions/raw/Flt1004_readme.txt
sgl2020/descriptions/raw/Flt1005_readme.txt
sgl2020/descriptions/raw/Flt1006_readme.txt
sgl2020/descriptions/raw/Flt1007_readme.txt
sgl2020/descriptions/raw/pilot_comments.csv
sgl2020/descriptions/raw/sgl_2020_fields_readme.txt
sgl2020-0.1.1.dist-info/METADATA
sgl2020-0.1.1.dist-info/WHEEL
sgl2020-0.1.1.dist-info/licenses/LICENSE
sgl2020-0.1.1.dist-info/RECORD
