Metadata-Version: 2.1
Name: sgl2020
Version: 0.1.1
Summary: Data Wrapper for SGL2020 Aeromagnetic Survey
Author-email: dorian <dorian.li@outlook.com>
License-File: LICENSE
Classifier: License :: OSI Approved :: MIT License
Classifier: Operating System :: OS Independent
Classifier: Programming Language :: Python :: 3
Requires-Python: >=3.9
Requires-Dist: h5py
Requires-Dist: numpy
Requires-Dist: pandas
Requires-Dist: pooch
Requires-Dist: prettytable
Requires-Dist: typing-extensions
